<?xml version="1.0" encoding="utf-8"?><rdf:RDF xmlns="http://purl.org/rss/1.0/" xmlns:rdf="http://www.w3.org/1999/02/22-rdf-syntax-ns#" xmlns:dc="http://purl.org/dc/elements/1.1/" xmlns:content="http://purl.org/rss/1.0/modules/content/" >
<channel><title>https://dengekionline.com/</title><dc:rights>portions by (c) KADOKAWA Game Linkage Inc.</dc:rights></channel>
<item rdf:about="/articles/132846/">
<description>『エヴァ』×『PUBG MOBILE』第2弾詳細発表！</description>
<dc:date>2022-05-19 21:30</dc:date> <link>https://dengekionline.com/articles/132846/</link></item>
<item rdf:about="/articles/132944/">
<description>『ヘブバン』リリース100日情報まとめ。明日からはSS確定入手のチャンスもあるのでログインしたほうがいい</description>
<dc:date>2022-05-19 21:14</dc:date> <link>https://dengekionline.com/articles/132944/</link></item>
<item rdf:about="/articles/132829/">
<description>ノイキャン搭載で1万円！ 軽量コンパクトなビクター完全ワイヤレスイヤホン</description>
<dc:date>2022-05-19 21:10</dc:date> <link>https://dengekionline.com/articles/132829/</link></item>
<item rdf:about="/articles/132802/">
<description>『三國志 真戦』1周年記念インタビュー公開。次シーズンの見どころや今後の展望は？</description>
<dc:date>2022-05-19 21:00</dc:date> <link>https://dengekionline.com/articles/132802/</link></item>
<item rdf:about="/articles/132671/">
<description>乙女は見ちゃダメ!? 男子のための男子ラジオをお届け『木村良平・岡本信彦のボイスマ』第15回今夜配信</description>
<dc:date>2022-05-19 20:45</dc:date> <link>https://dengekionline.com/articles/132671/</link></item>
<item rdf:about="/articles/132828/">
<description>映画『シン・ウルトラマン』のウルトラマンがでっかカワイイぬいぐるみに！</description>
<dc:date>2022-05-19 20:40</dc:date> <link>https://dengekionline.com/articles/132828/</link></item>
<item rdf:about="https://dengekionline.com/articles/132746/?osusume_banner" target="">
<description>スタイリッシュなデザインがズラリ</description>
<item rdf:about="https://youtu.be/K9OWt1koF4c/?kijilistbanner" target="">
<item rdf:about="/articles/132797/">
<description>アニメ『骸骨騎士様』7話。魔獣のボスが嵌めていたリングは…</description>
<dc:date>2022-05-19 20:30</dc:date> <link>https://dengekionline.com/articles/132797/</link></item>
<item rdf:about="/articles/132818/">
<description>アニメ『五等分の花嫁∬』黒ドレスの中野三玖がフィギュア化。質感のこだわりもすごい！</description>
<dc:date>2022-05-19 20:20</dc:date> <link>https://dengekionline.com/articles/132818/</link></item>
<item rdf:about="/articles/132884/">
<description>【エルデンリング】商人のアイテムは円卓でも買える！ ただし…【攻略動画】</description>
<dc:date>2022-05-19 20:00</dc:date> <link>https://dengekionline.com/articles/132884/</link></item>
<item rdf:about="/articles/132893/">
<description>豪華報酬ありの推しキャラキャンペーン開催中！ タグを追うのも楽しいよ【ゲトメア日記＃70】</description>
<dc:date>2022-05-19 19:50</dc:date> <link>https://dengekionline.com/articles/132893/</link></item>
<item rdf:about="/articles/132927/">
<description>『ウマ娘』“ぱかライブ TV”Vol.17は5/29配信</description>
<dc:date>2022-05-19 19:47</dc:date> <link>https://dengekionline.com/articles/132927/</link></item>
<item rdf:about="/articles/132931/">
<description>【電撃シンクロ日記＃37】第1界層 アナザーフェスで20連回したら……扉の隙間から虹色の輝きが見えた!!</description>
<dc:date>2022-05-19 19:45</dc:date> <link>https://dengekionline.com/articles/132931/</link></item>
<item rdf:about="https://dengekionline.com/articles/132925/?osusume_banner" target="">
<description>PVのクオリティに誰もが納得♡</description>
<item rdf:about="https://dengekionline.com/articles/128900/?kijilistbanner" target="">
<item rdf:about="/articles/132831/">
<description>『マインクラフト』エンダーマンのぬいぐるみはなんと50cm。素朴ながら不思議な魅力あり</description>
<dc:date>2022-05-19 19:40</dc:date> <link>https://dengekionline.com/articles/132831/</link></item>
<item rdf:about="/articles/132878/">
<description>『セインツロウ』の最新情報がメディア向けに公開！ さらに進化した“フリーダムさ”に期待できそう</description>
<dc:date>2022-05-19 19:20</dc:date> <link>https://dengekionline.com/articles/132878/</link></item>
<item rdf:about="/articles/132925/">
<description>や…やつらが動いとる!! アニメ『うる星やつら』10月放送開始。PVは期待が高まりまくるデキに</description>
<dc:date>2022-05-19 19:12</dc:date> <link>https://dengekionline.com/articles/132925/</link></item>
<item rdf:about="/articles/132800/">
<description>アニメ『サマータイムレンダ』6話。繰り返される7月22日…ひづるは島の真実を知る</description>
<dc:date>2022-05-19 19:10</dc:date> <link>https://dengekionline.com/articles/132800/</link></item>
<item rdf:about="/articles/132764/">
<description>『カリギュラ2』Steam版およびEpic Games Store版が発売決定！</description>
<dc:date>2022-05-19 19:00</dc:date> <link>https://dengekionline.com/articles/132764/</link></item>
<item rdf:about="/articles/132915/">
<description>『ナナリズムダッシュ』新コラボは『ぱちすろ けものフレンズ』。サーバル、キタキツネらが登場</description>
<dc:date>2022-05-19 18:45</dc:date> <link>https://dengekionline.com/articles/132915/</link></item>
<item rdf:about="https://dengekionline.com/articles/131261/?osusume_banner" target="">
<description>ソウルライク＆メトロイドヴァニア</description>
<item rdf:about="https://dengekionline.com/feature/sin-chronicle/?kijilistbanner" target="">
<item rdf:about="/articles/132854/">
<description>【ヘブバン日記#41】SS二階堂三郷、SS月城最中、S神崎アーデルハイドが上方修正。どこが変わったか確認</description>
<dc:date>2022-05-19 18:40</dc:date> <link>https://dengekionline.com/articles/132854/</link></item>
<item rdf:about="/articles/132875/">
<description>『ラブライブ！スーパースター!!』×楽天イーグルスグッズが予約開始！</description>
<dc:date>2022-05-19 18:30</dc:date> <link>https://dengekionline.com/articles/132875/</link></item>
<item rdf:about="/articles/132897/">
<description>『ますますマンガで分かる！ FGO』248話。寝込んだオフェリアがセイバーを呼ぶと!?</description>
<dc:date>2022-05-19 18:02</dc:date> <link>https://dengekionline.com/articles/132897/</link></item>
<item rdf:about="/articles/132750/">
<description>ボイスドラマ配信マーケット“ミミクル”サービス開始！</description>
<dc:date>2022-05-19 18:00</dc:date> <link>https://dengekionline.com/articles/132750/</link></item>
<item rdf:about="/articles/132820/">
<description>アニメ『デート・ア・ライブIV』花守ゆみりがニベルコル役で出演決定！</description>
<dc:date>2022-05-19 18:00</dc:date> <link>https://dengekionline.com/articles/132820/</link></item>
<item rdf:about="/articles/132867/">
<description>サントリー“ザ・マッカラン”でちょっと贅沢な一杯を、父の日に</description>
<dc:date>2022-05-19 17:50</dc:date> <link>https://dengekionline.com/articles/132867/</link></item>
<item rdf:about="https://dengekionline.com/articles/132600/?osusume_banner" target="">
<description>『百英雄伝』本編との繋がりも判明!?</description>
<item rdf:about="https://dengekionline.com/feature/dengeki_sangokushi/?kijilistbanner" target="">
<item rdf:about="/articles/132894/">
<description>『チェンクロ』謀略の姿の“ダスティ（声優：柳田淳一）”が登場する新世界フェス開始</description>
<dc:date>2022-05-19 17:45</dc:date> <link>https://dengekionline.com/articles/132894/</link></item>
<item rdf:about="/articles/132805/">
<description>数量限定37,800円！ Windows 11 Pro搭載8インチミニノートPC発売</description>
<dc:date>2022-05-19 17:40</dc:date> <link>https://dengekionline.com/articles/132805/</link></item>
<item rdf:about="/articles/132593/">
<description>ダメだこのエルフ…早くなんとかしないと…</description>
<dc:date>2022-05-19 17:30</dc:date> <link>https://dengekionline.com/articles/132593/</link></item>
<item rdf:about="/articles/132860/">
<description>猫を目隠しする理由は!? 話題の『もふもふマスク』が販売中！</description>
<dc:date>2022-05-19 17:26</dc:date> <link>https://dengekionline.com/articles/132860/</link></item>
<item rdf:about="/articles/132825/">
<description>『アーテリーギア』メカ×美少女たちのシリアスな物語とオートバトルの作り込みが魅力【電撃bilibili】</description>
<dc:date>2022-05-19 17:10</dc:date> <link>https://dengekionline.com/articles/132825/</link></item>
<item rdf:about="/articles/132794/">
<description>アニメ『キングダム』4期7話は激戦の予感。魏火龍の1人・凱孟に信が挑む！</description>
<dc:date>2022-05-19 17:00</dc:date> <link>https://dengekionline.com/articles/132794/</link></item>
<item rdf:about="https://dengekionline.com/articles/131196/?osusume_banner" target="">
<description>“しんにゅう”とちょっと似ているかも</description>
<item rdf:about="/articles/132834/">
<description>キャンプに最適な軽量カトラリー！ スノーピークの“武器”2本セットが販売中</description>
<dc:date>2022-05-19 16:50</dc:date> <link>https://dengekionline.com/articles/132834/</link></item>
<item rdf:about="/articles/132788/">
<description>『FF14 暁月のフィナーレ』人気BGM『FLOW』と共に冒険の思い出に浸れるMVが公開</description>
<dc:date>2022-05-19 16:30</dc:date> <link>https://dengekionline.com/articles/132788/</link></item>
<item rdf:about="/articles/132857/">
<description>KADOKAWA DREAMSのROUND.12使用楽曲『Symbol feat.T-Cray』配信スタート！</description>
<dc:date>2022-05-19 16:17</dc:date> <link>https://dengekionline.com/articles/132857/</link></item>
<item rdf:about="/articles/132762/">
<description>『ひぐらしのなく頃に 命』×『CLANNAD』コラボカード2弾が登場！</description>
<dc:date>2022-05-19 16:00</dc:date> <link>https://dengekionline.com/articles/132762/</link></item>
<item rdf:about="/articles/132789/">
<description>アニメ『パリピ孔明』8話で、KABEが劇的な変化を遂げたあいつと再会!?</description>
<dc:date>2022-05-19 15:30</dc:date> <link>https://dengekionline.com/articles/132789/</link></item>
<item rdf:about="/articles/132836/">
<description>『DQウォーク』ぶき錬成に聖女のこんが追加！ イベントのエンディングクエストも配信開始</description>
<dc:date>2022-05-19 15:27</dc:date> <link>https://dengekionline.com/articles/132836/</link></item>
<item rdf:about="https://dengekionline.com/articles/132485/?osusume_banner" target="">
<description>ウマ娘のガシャポンが可愛すぎ!?</description>
<item rdf:about="/articles/132761/">
<description>『ペルソナ』25周年記念コラボカフェ後期にはP2、P3、P5イメージメニューが登場</description>
<dc:date>2022-05-19 15:00</dc:date> <link>https://dengekionline.com/articles/132761/</link></item>
<item rdf:about="/articles/132770/">
<description>『モンハンライズ：サンブレイク』大剣・操虫棍・ハンマーの映像解禁！</description>
<dc:date>2022-05-19 14:30</dc:date> <link>https://dengekionline.com/articles/132770/</link></item>
<item rdf:about="/articles/132741/">
<description>『このすば』5/28生配信で新情報解禁か。はたして何の情報？</description>
<dc:date>2022-05-19 14:00</dc:date> <link>https://dengekionline.com/articles/132741/</link></item>
<item rdf:about="/articles/132785/">
<description>14インチHUAWEIノートPC新モデルが税込74,980円で登場</description>
<dc:date>2022-05-19 13:40</dc:date> <link>https://dengekionline.com/articles/132785/</link></item>
<item rdf:about="/articles/132779/">
<description>大阪王将のチャーハン＆水餃子簡単調理セットが期間限定セール中！</description>
<dc:date>2022-05-19 13:30</dc:date> <link>https://dengekionline.com/articles/132779/</link></item>
<item rdf:about="/articles/132787/">
<description>『ポケカ』強化拡張パック“Pokémon GO”の抽選販売応募は5/22まで！</description>
<dc:date>2022-05-19 13:28</dc:date> <link>https://dengekionline.com/articles/132787/</link></item>
<item rdf:about="https://dengekionline.com/articles/132451/?osusume_banner" target="">
<description>アーケード新作音ゲーのロケテスト実施日は？</description>
<item rdf:about="/articles/132781/">
<description>サンリオキャラクターズのかわいいヘアゴムがセブンイレブンでもらえる！</description>
<dc:date>2022-05-19 13:25</dc:date> <link>https://dengekionline.com/articles/132781/</link></item>
<item rdf:about="/articles/132739/">
<description>『マイクラ』たいまつ型インテリアライトが登場。これで自宅の湧き潰しもバッチリ？</description>
<dc:date>2022-05-19 13:00</dc:date> <link>https://dengekionline.com/articles/132739/</link></item>
<item rdf:about="/articles/132776/">
<description>『ポケモンHOME』と連携すると『ダイパリメイク』『レジェンズ アルセウス』で特別なポケモンがもらえる！</description>
<dc:date>2022-05-19 12:50</dc:date> <link>https://dengekionline.com/articles/132776/</link></item>
<item rdf:about="/articles/132774/">
<description>『ポケモンレジェンズ アルセウス』オリジナルアニメ第1話が公開！</description>
<dc:date>2022-05-19 12:46</dc:date> <link>https://dengekionline.com/articles/132774/</link></item>
<item rdf:about="/articles/132733/">
<description>『遊戯王 デュエルリンクス』イベント“神代璃緒出現！”でペンギン・ソルジャーを入手せよ！</description>
<dc:date>2022-05-19 12:40</dc:date> <link>https://dengekionline.com/articles/132733/</link></item>
<item rdf:about="/articles/132589/">
<description>スリットから覗く太ももにドキッ。新しいパジャマはチャイナ服！</description>
<dc:date>2022-05-19 12:30</dc:date> <link>https://dengekionline.com/articles/132589/</link></item>
<item rdf:about="https://dengekionline.com/articles/132416/?osusume_banner" target="">
<description>『ショーシャンクの空に』が金ロー初登場</description>
<item rdf:about="/articles/132765/">
<description>『ドラゴンボール』×『ビックリマン』コラボふたたび！ 5/24より東日本先行で販売開始</description>
<dc:date>2022-05-19 12:25</dc:date> <link>https://dengekionline.com/articles/132765/</link></item>
<item rdf:about="/articles/132772/">
<description>【ウマ娘ガチャ更新情報】明日、メジロパーマーが星3育成ウマ娘に！ サポカはSSRライスシャワー＆フクキタルのW復刻</description>
<dc:date>2022-05-19 12:21</dc:date> <link>https://dengekionline.com/articles/132772/</link></item>
</rdf:RDF>
