<?xml version="1.0" encoding="utf-8"?><rdf:RDF xmlns="http://purl.org/rss/1.0/" xmlns:rdf="http://www.w3.org/1999/02/22-rdf-syntax-ns#" xmlns:dc="http://purl.org/dc/elements/1.1/" xmlns:content="http://purl.org/rss/1.0/modules/content/" >
<channel><title>https://dengekionline.com/</title><dc:rights>portions by (c) KADOKAWA Game Linkage Inc.</dc:rights></channel>
<item rdf:about="/articles/102177/">
<description>『機動戦士ガンダム THE ORIGIN』展覧会のキービジュアル公開！ 限定ガンプラ情報も</description>
<dc:date>2021-10-26 13:10</dc:date> <link>https://dengekionline.com/articles/102177/</link></item>
<item rdf:about="/articles/102077/">
<description>『エヌ・イノセンス』鬼頭明里ら総勢12名のバラエティ番組が10/28に公開！</description>
<dc:date>2021-10-26 13:00</dc:date> <link>https://dengekionline.com/articles/102077/</link></item>
<item rdf:about="/articles/102095/">
<description>『ダンガンロンパ』10周年イベントの追加出演者が発表！</description>
<dc:date>2021-10-26 13:00</dc:date> <link>https://dengekionline.com/articles/102095/</link></item>
<item rdf:about="/articles/102035/">
<description>『86』原作イラストレーターのイラストを使用したオンラインくじが登場！</description>
<dc:date>2021-10-26 12:30</dc:date> <link>https://dengekionline.com/articles/102035/</link></item>
<item rdf:about="/articles/102189/">
<description>“第07板倉小隊”が4年ぶりに復活！ アーケード『ガンダム 戦場の絆』を紹介する番組が全8回で放送決定</description>
<dc:date>2021-10-26 12:20</dc:date> <link>https://dengekionline.com/articles/102189/</link></item>
<item rdf:about="https://dengekionline.com/articles/102048/">
<description>【10/25の気になるニュース】日本のゲーム業界、なぜ世界で存在感低下？／アマゾンギフト券、突然残高ゼロに／テレビ離れの実態</description>
<dc:date>2021-10-26 12:10</dc:date> <link>https://dengekionline.comhttps://dengekionline.com/articles/102048/</link></item>
<item rdf:about="https://dengekionline.com/articles/99025/?osusume_banner" target="">
<description>『テイルズ オブ』シリーズ新作レビュー</description>
<item rdf:about="/articles/101804/">
<description>『ダンガンロンパ』シリーズから人気キャラを選ぶ投票企画スタート！</description>
<dc:date>2021-10-26 11:45</dc:date> <link>https://dengekionline.com/articles/101804/</link></item>
<item rdf:about="/articles/89950/">
<description>さて、始めるとしようか……この帝国で再び花開く、僕のサクセスストーリーをねッ！ （ギルバート）【軌跡シリーズ名言集】</description>
<dc:date>2021-10-26 11:30</dc:date> <link>https://dengekionline.com/articles/89950/</link></item>
<item rdf:about="/articles/102028/">
<description>アニメ『プラオレ』4話。高校に入学した愛佳たちは正式にチームへ誘われる</description>
<dc:date>2021-10-26 11:00</dc:date> <link>https://dengekionline.com/articles/102028/</link></item>
<item rdf:about="/articles/102084/">
<description>『デッドバイデイライト モバイル』10/28よりセカンドベータ開催</description>
<dc:date>2021-10-26 10:30</dc:date> <link>https://dengekionline.com/articles/102084/</link></item>
<item rdf:about="/articles/102019/">
<description>コナミコマンド“↑↑↓↓←→←→BA”誕生から35周年！ 記念ポップアップショップがオープン!!</description>
<dc:date>2021-10-26 10:00</dc:date> <link>https://dengekionline.com/articles/102019/</link></item>
<item rdf:about="/articles/102090/">
<description>島本須美が『MAPLUSキャラdeナビ』に登場。あなたの行く道を優しく案内してくれる</description>
<dc:date>2021-10-26 09:30</dc:date> <link>https://dengekionline.com/articles/102090/</link></item>
<item rdf:about="https://dengekionline.com/articles/101195/?osusume_banner" target="">
<description>彼女がウマドルを目指すのはきっと理由がある</description>
<item rdf:about="/articles/102117/">
<description>『プリズマ☆イリヤ』初の展覧会が開催決定！ 11/26よりチケット発売開始</description>
<dc:date>2021-10-26 09:00</dc:date> <link>https://dengekionline.com/articles/102117/</link></item>
<item rdf:about="/articles/102007/">
<description>『トレクル』もうすぐ7.5周年！ プロデューサーからのメッセージ動画公開</description>
<dc:date>2021-10-26 08:30</dc:date> <link>https://dengekionline.com/articles/102007/</link></item>
<item rdf:about="/articles/102003/">
<description>『鬼滅の刃』×くら寿司コラボ開催。煉獄さんイメージの寿司ネタ、何かわかる？</description>
<dc:date>2021-10-26 08:00</dc:date> <link>https://dengekionline.com/articles/102003/</link></item>
<item rdf:about="/articles/101862/">
<description>4人目のアスタリスタも発表！ サプライズだらけのハーフアニバーサリーを振り返る!!【ユージェネ日記#60】</description>
<dc:date>2021-10-26 07:30</dc:date> <link>https://dengekionline.com/articles/101862/</link></item>
<item rdf:about="/articles/102018/">
<description>『ポケモンGO』まだ間に合う！ ハロウィンコスチュームを着たポケモンたち</description>
<dc:date>2021-10-26 07:10</dc:date> <link>https://dengekionline.com/articles/102018/</link></item>
<item rdf:about="/articles/101879/">
<description>【スタバ新作レポ】トリート with トリック フラペチーノはトッピングでもっとハロウィン気分に！</description>
<dc:date>2021-10-26 07:00</dc:date> <link>https://dengekionline.com/articles/101879/</link></item>
<item rdf:about="https://dengekionline.com/articles/102081/?osusume_banner" target="">
<description>黒バニー姿のレムがフィギュアに</description>
<item rdf:about="/articles/102136/">
<description>日和ってる奴いる？ いねえよなあ!!? 『東京リベンジャーズ』マイキーのセリフが印象的なクッション登場</description>
<dc:date>2021-10-26 06:40</dc:date> <link>https://dengekionline.com/articles/102136/</link></item>
<item rdf:about="/articles/100775/">
<description>美少女ゲームの皮をかぶったコンシューマライクな本格SRPG。『れじぇくろ！』から伝わる開発者の本気</description>
<dc:date>2021-10-26 06:30</dc:date> <link>https://dengekionline.com/articles/100775/</link></item>
<item rdf:about="/articles/102048/">
<description>『フォートナイト』が『バイオハザード』とコラボ／PS5発売もうすぐ1年／ガストブランドの集大成とも言える作品【電撃NOW】</description>
<dc:date>2021-10-26 06:20</dc:date> <link>https://dengekionline.com/articles/102048/</link></item>
<item rdf:about="/articles/101950/">
<description>アプリ『コードギアス』無料入手できるハロウィンギギは強いの？  入手方法は？</description>
<dc:date>2021-10-26 06:10</dc:date> <link>https://dengekionline.com/articles/101950/</link></item>
<item rdf:about="/articles/102176/">
<description>『DQウォーク』ミルドラースのこころは、バギ属性スキル特化と思いきや、じつは……!?【電撃DQW日記#1095】</description>
<dc:date>2021-10-26 06:00</dc:date> <link>https://dengekionline.com/articles/102176/</link></item>
<item rdf:about="/articles/102022/">
<description>サイコロジカルホラーとカードゲームが融合。『Inscryption』がSteamで配信中</description>
<dc:date>2021-10-26 00:00</dc:date> <link>https://dengekionline.com/articles/102022/</link></item>
<item rdf:about="https://dengekionline.com/articles/102163/?osusume_banner" target="">
<description>『スパロボ30』に『ULTRAMAN』『オルフェンズ』参戦</description>
<item rdf:about="/articles/102015/">
<description>ゲームブランドqureateが独立して新会社に。新作4本も発表！</description>
<dc:date>2021-10-25 23:00</dc:date> <link>https://dengekionline.com/articles/102015/</link></item>
<item rdf:about="/articles/102103/">
<description>ホロライブ“戌神ころね”が邪神に！ 『つぐのひ』新作が11/8発売</description>
<dc:date>2021-10-25 22:40</dc:date> <link>https://dengekionline.com/articles/102103/</link></item>
<item rdf:about="/articles/102171/">
<description>いよいよ明日、正式サービス『貞子M 未解決事件探偵事務所』事前ダウンロード開始</description>
<dc:date>2021-10-25 22:35</dc:date> <link>https://dengekionline.com/articles/102171/</link></item>
<item rdf:about="/articles/102063/">
<description>孫尚香、王異らが獲得可能！ 『三国覇王戦記』イベント“求賢三令”開催中</description>
<dc:date>2021-10-25 22:30</dc:date> <link>https://dengekionline.com/articles/102063/</link></item>
<item rdf:about="/articles/102163/">
<description>『スパロボ30』DLC2は『鉄血のオルフェンズ』＆『ULTRAMAN』が参戦。そしてキョウスケにエクセレンも!!</description>
<dc:date>2021-10-25 22:13</dc:date> <link>https://dengekionline.com/articles/102163/</link></item>
<item rdf:about="/articles/102082/">
<description>『グラサマ』ハロウィン限定の宝具召喚やレイドバトルが開催中！</description>
<dc:date>2021-10-25 22:10</dc:date> <link>https://dengekionline.com/articles/102082/</link></item>
<item rdf:about="https://dengekionline.com/articles/100775/?osusume_banner" target="">
<description>コンシューマライクの骨太バトルが楽しめる美少女SRPGをレビュー</description>
<item rdf:about="/articles/101982/">
<description>夜間の工事現場で出会う黒い女の恐怖…！ Switch『愛莉澄』発売</description>
<dc:date>2021-10-25 22:00</dc:date> <link>https://dengekionline.com/articles/101982/</link></item>
<item rdf:about="/articles/102156/">
<description>『オルサガ』ハロウィン衣装の17UR“アルベリク（声優：細谷佳正）”“オルタンス（声優：門脇舞以）”登場</description>
<dc:date>2021-10-25 21:51</dc:date> <link>https://dengekionline.com/articles/102156/</link></item>
<item rdf:about="/articles/101345/">
<description>『ガンダムX』33話が配信中。かつての英雄は、ガロードを通じて宿敵の今を知る</description>
<dc:date>2021-10-25 21:50</dc:date> <link>https://dengekionline.com/articles/101345/</link></item>
<item rdf:about="/articles/102036/">
<description>アニメ『マブラヴ オルタ』4話。武が戦術機の格納庫で見たものは</description>
<dc:date>2021-10-25 21:30</dc:date> <link>https://dengekionline.com/articles/102036/</link></item>
<item rdf:about="/articles/102126/">
<description>物理キーボードを隠し持つ5GスマホがMakuakeで先行販売</description>
<dc:date>2021-10-25 21:20</dc:date> <link>https://dengekionline.com/articles/102126/</link></item>
<item rdf:about="/articles/102074/">
<description>『三國志 真戦』Amazonギフト券が当たるイベントを開催！</description>
<dc:date>2021-10-25 21:10</dc:date> <link>https://dengekionline.com/articles/102074/</link></item>
<item rdf:about="https://dengekionline.com/articles/101195/?osusume_banner" target="">
<description>「そんなのアリ？」なウマ娘って？ ママキャラの裏にいる人とは</description>
<item rdf:about="/articles/102142/">
<description>『劇場版 呪術廻戦 0』原作者描き下ろしのムビチケ前売券発売決定！（※購入条件あり）</description>
<dc:date>2021-10-25 21:06</dc:date> <link>https://dengekionline.com/articles/102142/</link></item>
<item rdf:about="/articles/101955/">
<description>注目インディーなど計12本のゲームを紹介した9月【電撃インディー生放送まとめ】</description>
<dc:date>2021-10-25 21:00</dc:date> <link>https://dengekionline.com/articles/101955/</link></item>
<item rdf:about="/articles/102033/">
<description>式守さんお誕生日おめでとう！ 『可愛いだけじゃない式守さん』ロングPV公開</description>
<dc:date>2021-10-25 21:00</dc:date> <link>https://dengekionline.com/articles/102033/</link></item>
<item rdf:about="/articles/102043/">
<description>『ぷよクエ』“10月お得な10連ガチャ”開催中</description>
<dc:date>2021-10-25 20:50</dc:date> <link>https://dengekionline.com/articles/102043/</link></item>
<item rdf:about="/articles/102040/">
<description>『信長の野望・新生』の最新情報も！ シブサワ・コウ40周年記念番組の詳細が判明</description>
<dc:date>2021-10-25 20:30</dc:date> <link>https://dengekionline.com/articles/102040/</link></item>
<item rdf:about="/articles/102148/">
<description>『プリコネR』11/3から最大70連ガチャが無料！</description>
<dc:date>2021-10-25 20:25</dc:date> <link>https://dengekionline.com/articles/102148/</link></item>
<item rdf:about="https://dengekionline.com/articles/101795/?osusume_banner" target="">
<description>MSX2版『魔導物語』の思い出も!?</description>
<item rdf:about="/articles/102094/">
<description>『フィギュアストーリー』水城結奈の新スキン“蜜色の幻想Ver.”が登場</description>
<dc:date>2021-10-25 20:20</dc:date> <link>https://dengekionline.com/articles/102094/</link></item>
<item rdf:about="https://dengekionline.com/articles/100591/">
<description>『ガールフレンド（仮）』9周年記念生放送が26日20時30分より配信！ 豪華キャストとお祝いしよう</description>
<dc:date>2021-10-25 20:15</dc:date> <link>https://dengekionline.comhttps://dengekionline.com/articles/100591/</link></item>
<item rdf:about="/articles/102024/">
<description>MF文庫J『聖剣学院の魔剣使い』アニメ化企画進行中！</description>
<dc:date>2021-10-25 20:10</dc:date> <link>https://dengekionline.com/articles/102024/</link></item>
<item rdf:about="/articles/101949/">
<description>RazerがヘッドセットやWEBカメラなど4製品を国内発売決定！</description>
<dc:date>2021-10-25 20:00</dc:date> <link>https://dengekionline.com/articles/101949/</link></item>
<item rdf:about="/articles/102071/">
<description>Yostar、初のオリジナルアニメ『空色ユーティリティ』の制作を発表</description>
<dc:date>2021-10-25 19:30</dc:date> <link>https://dengekionline.com/articles/102071/</link></item>
<item rdf:about="/articles/101195/">
<description>【ウマ娘が1.8倍楽しくなるお話 13】そんなのアリ？ だからこそおもしろい！ ってお話</description>
<dc:date>2021-10-25 19:20</dc:date> <link>https://dengekionline.com/articles/101195/</link></item>
<item rdf:about="https://dengekionline.com/articles/101548/?osusume_banner" target="">
<description>TPS『ガンゲイル・オンライン』がお得なのでぜひご一読を！</description>
<item rdf:about="/articles/102140/">
<description>無限城が六本木に顕現!? 10/26より開催する鬼滅の刃原画展内覧会をレポート</description>
<dc:date>2021-10-25 19:16</dc:date> <link>https://dengekionline.com/articles/102140/</link></item>
<item rdf:about="/articles/101391/">
<description>前田佳織里と秋の電撃おすすめインディータイトルを紹介！ 10月28日「電撃ゲームライブ」拡大版を配信</description>
<dc:date>2021-10-25 19:15</dc:date> <link>https://dengekionline.com/articles/101391/</link></item>
</rdf:RDF>
