<?xml version="1.0" encoding="utf-8"?><rdf:RDF xmlns="http://purl.org/rss/1.0/" xmlns:rdf="http://www.w3.org/1999/02/22-rdf-syntax-ns#" xmlns:dc="http://purl.org/dc/elements/1.1/" xmlns:content="http://purl.org/rss/1.0/modules/content/" >
<channel><title>お天気ニュース</title><dc:rights>portions by © ウェザーニュース</dc:rights></channel>
<item rdf:about="202408090195_1723191300_1723191360">
<title>明日8月10日(土)対象の熱中症警戒アラート　関東から西の20都県</title>
<description><![CDATA[環境省と気象庁は、三連休初日となる明日8月10日(土)を対象とした熱中症警戒アラートを関東から西日本の20都県に発表しました。<br><br>対象地域では特に熱中症のリスクが高くなります。こまめな水分補給を心がけるとともに、屋外での長時間の行動を避けて室内でエアコンを使用するなど、熱中症予防を万全に行ってください。<br><a href="https://weathernews.jp/s/heatstroke/?fm=news" class="dmenu-non smartnews" onclick='javascript:ga_and_go(this.href,"文中リンク_熱中症情報"); return false'>» 熱中症情報 暑さ指数(WBGT)を確認</a> ◆ 【明日の熱中症警戒アラート】環境省と気象庁は、三連休初日となる明日8月10日(土)を対象とした熱中症警戒アラートを関東から西日本の20都県に発表しました。こまめな水分補給などの熱中症予防はもちろん、エアコンの効いた涼しい室内で過ごすなど積極的に熱中症を防止する行動をとってください。]]></description>
<dc:date>2024-08-09T17:16:00+09:00</dc:date>
<link>https://weathernews.jp/s/topics/202408/090195/</link></item>
<item rdf:about="202408090205_1723190400_1723190220">
<title>明日10日(土)の天気予報 三連休初日は東海以西で危険な暑さ　関東は天気急変に注意</title>
<description><![CDATA[<div style="max-width: 360px; margin-right:auto; margin-left:auto;"><div style="border: 1px solid #012; border-radius: 8px; padding: 4px; color: #012; position: relative;"><div style="text-align: center; font-weight: bold;">■ 天気のポイント ■</div>・東日本や西日本は強い日照で気温上昇<br>・関東や九州南部などは急な雷雨に注意<br>・太平洋沿岸は強風や高波に注意<br></div></div><br>三連休初日となる10日(土)は関東から西日本で強い日差しが照りつけます。引き続き気温が高く、特に東海以西は危険な暑さに警戒が必要です。また、関東や九州南部などでは天気の急変にもご注意ください。<br><a href="https://weathernews.jp/onebox/gps.html?fm=news" class="dmenu-non web smartnews">» GPS検索 ピンポイント天気予報</a><a href="weathernews://weathernews.jp/pinpoint" class="app">» ピンポイント天気予報</a> ◆ 三連休初日となる10日(土)は関東から西日本で強い日差しが照りつけます。引き続き気温が高く、特に東海以西は危険な暑さに警戒が必要です。また、関東や九州南部などでは天気の急変にもご注意ください。]]></description>
<dc:date>2024-08-09T16:57:00+09:00</dc:date>
<link>https://weathernews.jp/s/topics/202408/090205/</link></item>
<item rdf:about="202408090245_1723188960_1723188900">
<title>関東など内陸部を中心にゲリラ雷雨　道路冠水や落雷、突風に注意</title>
<description><![CDATA[今日9日(金)も午後になって所々で雨雲が発生・発達し、ゲリラ雷雨となっています。関東など一部では平野部にも雷雲が流れ込み、土砂降りの雨になっている状況です。夜にかけて道路冠水や落雷、突風などに注意し、雨が強い間の無理な移動は控えてください。 ◆ 今日も午後になって所々で雨雲が発生・発達し、ゲリラ雷雨となっています。関東など一部では平野部にも雷雲が流れ込み、土砂降りの雨になっている状況です。夜にかけて道路冠水や落雷、突風などに注意し、雨が強い間の無理な移動は控えてください。]]></description>
<dc:date>2024-08-09T16:35:00+09:00</dc:date>
<link>https://weathernews.jp/s/topics/202408/090245/</link></item>
<item rdf:about="202408090185_1723188000_1723188900">
<title>台風5号　三連休の交通機関への影響予測（9日16時更新）</title>
<description><![CDATA[三連休の最終日12日(月・祝)は、台風5号の影響で東北を中心に雨や風が強まり、鉄道や高速道路など公共の交通機関に影響が出ることが懸念されます。<br><br>お盆休みで東北方面へ旅行や遠出を予定されている場合は、あらかじめスケジュール変更なども視野に入れておいた方がよさそうです。<br><a href="https://weathernews.jp/s/typhoon/pinpoint.html?fm=news" class="dmenu-non smartnews" >» 台風ピンポイント影響予測（要ログイン）</a> ◆ 三連休の最終日12日(月・祝)は、台風5号の影響で東北を中心に雨や風が強まり、鉄道や高速道路など公共の交通機関に影響が出ることが懸念されます。お盆休みで旅行や遠出を予定されている場合は、あらかじめスケジュール変更なども視野に入れておいた方がよさそうです。]]></description>
<dc:date>2024-08-09T16:35:00+09:00</dc:date>
<link>https://weathernews.jp/s/topics/202408/090185/</link></item>
<item rdf:about="202408090225_1723186860_1723186500">
<title>三重県で初の40℃、名古屋も39℃を観測　明日も危険な暑さ続く</title>
<description><![CDATA[今日9日(金)は西日本や東日本を中心に晴れて、気温が上がりました。三重県では観測史上初めて40℃に到達した所があり、名古屋市も体温を大きく上回る39℃を観測しています。明日10日(土)も危険な暑さが続くため、熱中症に警戒が必要です。 ◆ 今日は西日本や東日本を中心に晴れて、気温が上がりました。三重県では観測史上初めて40℃に到達した所があり、名古屋市も体温を大きく上回る39℃を観測しています。明日10日(土)も危険な暑さが続くため、熱中症に警戒が必要です。]]></description>
<dc:date>2024-08-09T15:55:00+09:00</dc:date>
<link>https://weathernews.jp/s/topics/202408/090225/</link></item>
<item rdf:about="202408090095_1723185600_1723184760">
<title>エルニーニョ現象は終息　今後はラニーニャ現象発生の可能性(エルニーニョ監視速報)</title>
<description><![CDATA[気象庁は9日(金)に最新のエルニーニョ監視速報を発表しました。エルニーニョ監視海域の海面水温は平常の範囲内になり、エルニーニョ現象は終息しています。<br><br>今後、冬にかけてはラニーニャ現象の発生する可能性が高い状況です。 ◆ 気象庁は9日(金)に最新のエルニーニョ監視速報を発表しました。エルニーニョ監視海域の海面水温は平常の範囲内になり、エルニーニョ現象は終息しています。今後、冬にかけてはラニーニャ現象の発生する可能性が高い状況です。]]></description>
<dc:date>2024-08-09T15:26:00+09:00</dc:date>
<link>https://weathernews.jp/s/topics/202408/090095/</link></item>
<item rdf:about="202408090145_1723184400_1723182960">
<title>台風進路図の予報円の大きさ＝台風の「強さ」や「大きさ」ではない</title>
<description><![CDATA[台風5号が日本列島に近づいてきています。週末からの三連休やお盆期間に影響をもたらす可能性が高くなってきました。<br><br>台風5号の予想進路図では、来週の予報円が非常に大きくなっています。ただし、これは台風が発達したり、サイズが大きくなることを示しているのではありません。 ◆ 台風5号が日本列島に近づいてきています。週末からの三連休やお盆期間に影響をもたらす可能性が高くなってきました。台風5号の予想進路図では来週の予報円が非常に大きくなっています。ただし、これは台風が発達したり、サイズが大きくなることを示しているのではありません。予報円の意味を正しく理解し、活用するようにしてください。]]></description>
<dc:date>2024-08-09T14:56:00+09:00</dc:date>
<link>https://weathernews.jp/s/topics/202408/090145/</link></item>
<item rdf:about="202408090135_1723183200_1723183200">
<title>週間天気　三連休は台風直撃のおそれ　東日本・西日本は天気急変に注意</title>
<description><![CDATA[<div style="max-width: 360px; margin-right:auto; margin-left:auto;"><div style="border: 1px solid #012; border-radius: 8px; padding: 4px; color: #012; position: relative;"><div style="text-align: center; font-weight: bold;">■この先1週間のポイント■</div>・三連休は台風5号が東北直撃のおそれ<br>・お盆休み期間中は大気不安定<br>・体温超えの暑さとなるところも<br>・ペルセウス座流星群が見頃に<br></div></div><br>三連休に台風が直撃するおそれが出てきました。交通機関への影響も懸念されるため、帰省や旅行の移動は計画的に。<br><a href="https://weathernews.jp/onebox/tenki/week/?fm=news" class="dmenu-non web smartnews" >» 全国の週間天気予報</a><a href="weathernews://weathernews.jp/pinpoint?mode=week" class="app" >» 週間天気予報</a> ◆ この先1週間の天気のポイントは「三連休は台風5号が東北直撃のおそれ」「お盆休み期間中は大気不安定」「体温超えの暑さとなるところも」「ペルセウス座流星群が見頃に」です。ウェザーニュースの最新の天気予報を随時確認してください。]]></description>
<dc:date>2024-08-09T15:00:00+09:00</dc:date>
<link>https://weathernews.jp/s/topics/202408/090135/</link></item>
<item rdf:about="202408080165_1723181400_1723182120">
<title>【速報】三重県桑名市で40℃を記録　三重県では初めての40℃観測</title>
<description><![CDATA[今日8月9日(金)の午後、三重県桑名市で40℃を記録しました。三重県で40℃に到達するのは観測史上初のこととなります。今年2024年では8回目の40℃到達です。<br><a href="https://weathernews.jp/onebox/amedas/?fm=news" class="dmenu-non">» 全国のアメダス観測値・ランキング</a> ◆ 今日8月9日(金)の午後、三重県桑名市で40℃を記録しました。三重県で40℃に到達するのは観測史上初のこととなります。今年2024年では8回目の40℃到達です。]]></description>
<dc:date>2024-08-09T14:42:00+09:00</dc:date>
<link>https://weathernews.jp/s/topics/202408/080165/</link></item>
<item rdf:about="202408090125_1723173180_1723173060">
<title>午前中から猛暑日地点が100地点超え　名古屋は40℃近くまで上がる可能性</title>
<description><![CDATA[今日9日(金)も朝から強い日差しが照りつけています。早いペースで気温が上がり、すでに35℃以上の猛暑日地点が100地点を超えました。名古屋市は16日連続の猛暑日になっています。熱中症に厳重な警戒が必要です。 ◆ 今日も朝から強い日差しが照りつけています。午前中のうちに35℃以上の猛暑日地点が100地点を超えました。午後はさらに気温が上がり、名古屋市など40℃近くまで上がる可能性があります。熱中症に厳重な警戒が必要です。]]></description>
<dc:date>2024-08-09T12:11:00+09:00</dc:date>
<link>https://weathernews.jp/s/topics/202408/090125/</link></item>
<item rdf:about="202408090105_1723170420_1723170300">
<title>台風5号　三連休やお盆期間に日本へ接近　東北に上陸する可能性も</title>
<description><![CDATA[8月9日(金)9時現在、台風5号（マリア）は暴風域を伴って日本の東の海上を北北東に進んでいます。引き続き進路の不確実性が大きいものの、三連休最終日に北日本にかなり接近すると見込まれ、上陸する可能性があります。<br><br>▼台風5号　8月9日(金)9時<br>　中心位置　　　日本の東<br>　大きさ階級　　／／<br>　強さ階級　　　／／<br>　移動　　　　　北北東　20 km/h<br>　中心気圧　　　980 hPa<br>　最大風速　　　30 m/s (中心付近)<br>　最大瞬間風速　40 m/s<br><a href="https://weathernews.jp/onebox/typhoon/?fm=news" class="dmenu-non web smartnews">» 最新の台風情報</a><a href="weathernews://weathernews.jp/typhoon" class="app">» 最新の台風情報</a><br><br><p align="center" class="dmenu-non"><span class="web"><a href="https://weathernews.jp/s/download/weathernewstouch.html?fm=news" target="_blank" rel="noopener noreferrer"><img src="https://weathernews.jp/ip/info/topics/img/ty_alarm_B.png" style="width: 100%; max-width: 320px;" onload="ad4hook()" alt="リンク ウェザーニュースアプリをDL"></a></span><span class="app"><a href="https://weathernews.jp/ip/info/smartalarm/typh.html?fm=news"><img src="https://weathernews.jp/ip/info/topics/img/ty_alarm_B.png" style="width: 100%; max-width: 320px;" onload="ad4hook()" alt="リンク 台風アラーム"></a></span></p><div class="dmenu-non" align="center"><p style="max-width: 640px; text-align: left; font-size: 90%;">ウェザーニュースアプリでお天気アラームを設定すると、今いる場所の天気・台風・地震・津波などの情報をいち早くプッシュ通知で受け取れます。</p></div> ◆ 【台風情報】8月9日(金)9時現在、台風5号（マリア）は日本の東の海上を暴風域を伴って発達しながら北上中です。引き続き進路の不確実性が大きいものの、三連休最終日に北日本にかなり接近すると見込まれ、上陸する可能性があります。]]></description>
<dc:date>2024-08-09T11:25:00+09:00</dc:date>
<link>https://weathernews.jp/s/topics/202408/090105/</link></item>
<item rdf:about="202408080185_1723168800_1723170480">
<title>ビール需要は気温や天気で大きく変化　猛暑日で8割が飲みたい</title>
<description><![CDATA[各地で最高気温40℃が観測されるなど、この夏も各地で危険な暑さが続いています。<br><br>暑い日はビールが飲みたくなる方が多くなると思いますが、その飲みたくなる境目はどこにあるのでしょうか。お天気アプリ「ウェザーニュース」を通して、ユーザーのみなさんが感じる“ビール日和”について調査しました。 ◆ 【ビール調査】各地で最高気温40℃が観測されるなど、この夏も各地で危険な暑さが続いています。 暑い日はビールが飲みたくなる方が多くなると思いますが、その飲みたくなる境目はどこにあるのでしょうか。お天気アプリ「ウェザーニュース」を通して、ユーザーのみなさんが感じる“ビール日和”について調査しました。]]></description>
<dc:date>2024-08-09T11:28:00+09:00</dc:date>
<link>https://weathernews.jp/s/topics/202408/080185/</link></item>
<item rdf:about="202408090115_1723168140_1723167000">
<title>今日も広い範囲で大気の状態が不安定　午後を中心にゲリラ雷雨に注意</title>
<description><![CDATA[今日9日(金)も広い範囲で大気の状態が不安定です。急に雨雲が発生・発達し、局地的にゲリラ雷雨となる可能性があります。特に屋外でレジャーを予定されている方は、熱中症と合わせて急な雷雨にご注意ください。<br><a href="https://weathernews.jp/app/rd/?param=hiresradar%3Fgps%3D1%26mode%3Dgrisk&fm=news" class="dmenu-non web smartnews" target="_blank">» レーダー 「ゲリラ雷雨リスク」モードをアプリで見る</a><a href="weathernews://weathernews.jp/hiresradar?gps=1&mode=grisk" class="app">» レーダー 「ゲリラ雷雨リスク」モード</a> ◆ 今日も広い範囲で大気の状態が不安定です。急に雨雲が発生・発達し、局地的にゲリラ雷雨となる可能性があります。特に屋外でレジャーを予定されている方は、熱中症と合わせて急な雷雨にご注意ください。]]></description>
<dc:date>2024-08-09T10:30:00+09:00</dc:date>
<link>https://weathernews.jp/s/topics/202408/090115/</link></item>
<item rdf:about="202408090085_1723163640_1723163280">
<title>北海道で局地的に土砂降りの雨　午後にかけて雨の範囲は東へ</title>
<description><![CDATA[今日9日(金)は北海道で雨の強まっている所があります。昼頃にかけては道央や道北を中心に、午後は道東オホーツク海側を中心に土砂降りの雨になる可能性があるため、注意が必要です。 ◆ 今日は北海道で雨の強まっている所があります。昼頃にかけては道央や道北を中心に、午後は道東オホーツク海側を中心に土砂降りの雨になる可能性があるため、注意が必要です。]]></description>
<dc:date>2024-08-09T09:28:00+09:00</dc:date>
<link>https://weathernews.jp/s/topics/202408/090085/</link></item>
<item rdf:about="202408090075_1723157100_1723157040">
<title>名古屋など39℃予想　東海や近畿を中心に今日も危険な暑さに</title>
<description><![CDATA[今日8月9日(金)も関東から西の地域では猛暑が続く見込みです。特に東海や近畿を中心に気温が上昇しやすく、名古屋市や岐阜市では予想最高気温が39℃と体温を上回る危険な暑さが予想されています。<br><br>引き続き、エアコンの効いた室内で過ごす、こまめに水分補給や塩分補給をするなど、できる限りの熱中症予防を行ってください。<br><a href="https://weathernews.jp/heatstroke/?fm=news" class="dmenu-non smartnews" >» 熱中症情報 暑さ指数(WBGT)を確認</a> ◆ 今日8月9日(金)も関東から西の地域では猛暑が続く見込みです。特に東海や近畿を中心に気温が上昇しやすく、名古屋市や岐阜市では予想最高気温が39℃と体温を上回る危険な暑さが予想されています。エアコンの効いた室内で過ごす、こまめに水分補給や塩分補給をするなど、できる限りの熱中症予防を行ってください。]]></description>
<dc:date>2024-08-09T07:44:00+09:00</dc:date>
<link>https://weathernews.jp/s/topics/202408/090075/</link></item>
<item rdf:about="202408090025_1723155300_1723155600">
<title>台風5号が三連休やお盆期間に日本接近か　西寄りに進むと影響大きくなるおそれ</title>
<description><![CDATA[8月9日(金)6時現在、台風5号（マリア）は日本の東の海上を北北東に進んでいます。勢力を強めて暴風域を伴うようになりました。進路の不確実性が大きいものの、三連休明けにかけて北日本に接近する可能性があり、注意が必要です。<br><br>▼台風5号　8月9日(金)6時<br>　中心位置　　　日本の東<br>　大きさ階級　　／／<br>　強さ階級　　　／／<br>　移動　　　　　北北東　20 km/h<br>　中心気圧　　　980 hPa<br>　最大風速　　　30 m/s (中心付近)<br>　最大瞬間風速　40 m/s<br><a href="https://weathernews.jp/onebox/typhoon/?fm=news" class="dmenu-non web smartnews">» 最新の台風情報</a><a href="weathernews://weathernews.jp/typhoon" class="app">» 最新の台風情報</a><br><br><p align="center" class="dmenu-non"><span class="web"><a href="https://weathernews.jp/s/download/weathernewstouch.html?fm=news" target="_blank" rel="noopener noreferrer"><img src="https://weathernews.jp/ip/info/topics/img/ty_alarm_B.png" style="width: 100%; max-width: 320px;" onload="ad4hook()" alt="リンク ウェザーニュースアプリをDL"></a></span><span class="app"><a href="https://weathernews.jp/ip/info/smartalarm/typh.html?fm=news"><img src="https://weathernews.jp/ip/info/topics/img/ty_alarm_B.png" style="width: 100%; max-width: 320px;" onload="ad4hook()" alt="リンク 台風アラーム"></a></span></p><div class="dmenu-non" align="center"><p style="max-width: 640px; text-align: left; font-size: 90%;">ウェザーニュースアプリでお天気アラームを設定すると、今いる場所の天気・台風・地震・津波などの情報をいち早くプッシュ通知で受け取れます。</p></div> ◆ 【台風情報】8月9日(金)6時現在、台風5号（マリア）は日本の東の海上を暴風域を伴って発達しながら北上中です。進路の不確実性が大きいものの、三連休明けにかけて北日本に接近する可能性があり、注意が必要です。]]></description>
<dc:date>2024-08-09T07:20:00+09:00</dc:date>
<link>https://weathernews.jp/s/topics/202408/090025/</link></item>
<item rdf:about="202408090055_1723150800_1723155060">
<title>関東甲信〜沖縄の30都府県に熱中症警戒アラート　涼しい所で過ごして</title>
<description><![CDATA[今日8月9日(金)、環境省と気象庁は熱中症警戒アラートを関東甲信〜沖縄の30都府県に発表しました。<br><br>対象地域では特に熱中症のリスクが高くなります。こまめな水分補給を心がけるとともに、屋外での長時間の行動を避けて室内でエアコンを使用するなど、熱中症予防を万全に行ってください。<br><a href="https://weathernews.jp/s/heatstroke/?fm=news" class="dmenu-non smartnews" onclick='javascript:ga_and_go(this.href,"文中リンク_熱中症情報"); return false'>» 熱中症情報 暑さ指数(WBGT)を確認</a> ◆ 【熱中症警戒アラート】環境省と気象庁は熱中症警戒アラートを関東甲信〜沖縄の30都府県に発表しました。こまめな水分補給などの熱中症予防はもちろん、エアコンの効いた涼しい室内で過ごすなど積極的に熱中症を防止する行動をとってください。]]></description>
<dc:date>2024-08-09T07:11:00+09:00</dc:date>
<link>https://weathernews.jp/s/topics/202408/090055/</link></item>
<item rdf:about="202408090035_1723150200_1723149180">
<title>週間天気　三連休やお盆休み中は台風や天気急変に注意</title>
<description><![CDATA[<div style="max-width: 360px; margin-right:auto; margin-left:auto;"><div style="border: 1px solid #012; border-radius: 8px; padding: 4px; color: #012; position: relative;"><div style="text-align: center; font-weight: bold;">■この先1週間のポイント■</div>・お盆休み期間中は大気不安定<br>・三連休は体温超えの暑さとなるところも<br>・台風5号や熱帯低気圧の動向に注目<br>・ペルセウス座流星群が見頃に<br></div></div><br>三連休からお盆休み後半にかけて、日本付近は気温が高く大気の状態が不安定になる日が多い予想です。また、台風の動向にも注意が必要です。<br><a href="https://weathernews.jp/onebox/tenki/week/?fm=news" class="dmenu-non web smartnews" >» 全国の週間天気予報</a><a href="weathernews://weathernews.jp/pinpoint?mode=week" class="app" >» 週間天気予報</a> ◆ この先1週間の天気のポイントは「お盆休み期間中は大気不安定」「三連休は体温超えの暑さとなるところも」「台風5号や熱帯低気圧の動向に注目」「ペルセウス座流星群が見頃に」です。ウェザーニュースの最新の天気予報を随時確認してください。]]></description>
<dc:date>2024-08-09T05:33:00+09:00</dc:date>
<link>https://weathernews.jp/s/topics/202408/090035/</link></item>
<item rdf:about="202408090045_1723150140_1723151160">
<title>ひと目でわかる傘マップ　8月9日(金)</title>
<description><![CDATA[今日8月9日(金)の外出の際に傘の持参が必要なエリアを解説します。<br><a href="https://weathernews.jp/s/topics/202408/090015/" class="dmenu-non smartnews">» 関連記事 今日の天気予報</a> ◆ 今日雨が降るエリア、傘が必要なエリアを詳しく解説します。ウェザーニュース天気予報。]]></description>
<dc:date>2024-08-09T06:06:00+09:00</dc:date>
<link>https://weathernews.jp/s/topics/202408/090045/</link></item>
<item rdf:about="202408080115_1723149960_1723150500">
<title>8月9日(金)の洗濯天気予報　東京や名古屋、大阪など乾き早い</title>
<description><![CDATA[今日の天気で、洗濯物を外干しできるかどうかをお伝えします。<br><a href="https://weathernews.jp/onebox/gps.html?fm=news" class="dmenu-non web smartnews" >» GPS検索 ピンポイント天気予報</a><a href="weathernews://weathernews.jp/pinpoint" class="app" >» ピンポイント天気予報</a> ◆ 今日の天気で洗濯物を外干しできるかどうかをお伝えします。乾くまでに何時間かかるか、洗濯物の種類によっての違いなど、ピンポイントの予報はウェザーニュースの「お洗濯情報」からご覧頂けます。]]></description>
<dc:date>2024-08-09T05:55:00+09:00</dc:date>
<link>https://weathernews.jp/s/topics/202408/080115/</link></item>
<item rdf:about="202408090065_1723149900_1723149720">
<title>お天気キャスター解説　8月9日(金)の天気</title>
<description><![CDATA[<div class="youtube"><iframe width="560" height="315" src="https://www.youtube.com/embed/o6dzs3OIse0" title="YouTube video player" frameborder="0" allow="accelerometer; autoplay; clipboard-write; encrypted-media; gyroscope; picture-in-picture" allowfullscreen></iframe></div>きょう8月9日(金)の全国の天気をウェザーニュースキャスターの小川千奈がお伝えします。 ◆ ウェザーニュースのお天気キャスターから、きょうの天気をお届けします。]]></description>
<dc:date>2024-08-09T05:42:00+09:00</dc:date>
<link>https://weathernews.jp/s/topics/202408/090065/</link></item>
<item rdf:about="202408090015_1723148700_1723148940">
<title>今日9日(金)の天気予報　東北〜西日本にかけては猛暑と雷雨注意　北海道でも雨</title>
<description><![CDATA[<div style="max-width: 360px; margin-right:auto; margin-left:auto;"><div style="border: 1px solid #012; border-radius: 8px; padding: 4px; color: #012; position: relative;"><div style="text-align: center; font-weight: bold;">■ 天気のポイント ■</div>・西日本、東日本は猛暑と雷雨に注意<br>・東北は日差し届いても油断は禁物<br>・北海道は断続的に雨で強く降る所も<br></div></div><br>今日9日(金)は西日本、東日本で晴れるところが多く、厳しい暑さが続きます。体温を大きく上回る猛烈な暑さのところもあり、熱中症対策が欠かせません。ただ、午後を中心に雷雨に注意が必要です。<br><br>北海道は気圧の谷の通過で断続的に雨が降り、強く降ることもあります。<br><a href="https://weathernews.jp/onebox/gps.html?fm=news" class="dmenu-non web smartnews">» GPS検索 ピンポイント天気予報</a><a href="weathernews://weathernews.jp/pinpoint" class="app">» ピンポイント天気予報</a> ◆ 今日9日(金)は西日本、東日本で晴れるところが多く、厳しい暑さが続きます。体温を大きく上回る猛烈な暑さのところもあり、熱中症対策が欠かせません。ただ、午後を中心に雷雨に注意が必要です。  北海道は気圧の谷の通過で断続的に雨が降り、強く降ることもあります。]]></description>
<dc:date>2024-08-09T05:29:00+09:00</dc:date>
<link>https://weathernews.jp/s/topics/202408/090015/</link></item>
<item rdf:about="202408080125_1723147800_1723147140">
<title>あなたは硬い派？柔らかい派？ 好みの桃が一目でわかる“桃チャート”</title>
<description><![CDATA[姿が美しく、みずみずしくて甘い桃。7月ごろの早生(わせ)を皮切りに、さまざまな品種が順に旬を迎えています。<br><br>桃は同じような見た目をしていても、品種によって甘さも食感も大きく異なります。山形県天童市の果樹農家、ヒロ・スマイルファームの後藤広美さんに伺いました。 ◆ 姿が美しく、みずみずしくて甘い桃。7月ごろの早生(わせ)を皮切りに、さまざまな品種が順に旬を迎えています。桃は同じような見た目をしていても、品種によって甘さも食感も大きく異なります。主な品種別に甘さと果肉の硬さをチャートでみてみましょう。]]></description>
<dc:date>2024-08-09T04:59:00+09:00</dc:date>
<link>https://weathernews.jp/s/topics/202408/080125/</link></item>
<item rdf:about="202408080005_1723147200_1723147200">
<title>今日のこよみ・今週のこよみ 2024年8月9日(金)</title>
<description><![CDATA[2024年8月9日(金)<br>旧暦7月6日　赤口<br>乙巳（きのと み）<br>十二直 おさん<br><br>潮回り 中潮<br>正午月齢 4.7<br>正午月相 4.0 ◆ 今日2024年8月9日(金)の旧暦、六曜、干支、中段十二直、雑節、潮回り、月齢、月相、日の出、日の入り、月の出、月の入りなどをご紹介します。来週にかけての暦の概要もご確認いただけます。]]></description>
<dc:date>2024-08-09T05:00:00+09:00</dc:date>
<link>https://weathernews.jp/s/topics/202408/080005/</link></item>
<item rdf:about="202408090423quake_1723144980_1723147140">
<title>日向灘でM5.3の地震　宮崎県で震度3　津波の心配なし</title>
<description><![CDATA[8月9日(金)4時23分頃、宮崎県で最大震度3を観測する地震がありました。この地震による津波の心配はありません。<br><br>震源地：日向灘<br>マグニチュード：5.3<br>震源の深さ：約20km<br><a href="https://weathernews.jp/quake/?fm=news" class="dmenu-non web smartnews" >» 地震情報一覧</a><a href="weathernews://weathernews.jp/quake" class="app" >» 地震情報一覧</a> ◆ 8月9日(金)4時23分頃、宮崎県で最大震度3を観測する地震がありました。この地震による津波の心配はありません。震源地は日向灘、地震の規模を示すマグニチュード(M)は5.3、震源の深さは約20kmとみられます。]]></description>
<dc:date>2024-08-09T04:59:00+09:00</dc:date>
<link>https://weathernews.jp/s/topics/202408/090423quake/</link></item>
<item rdf:about="202408080225_1723122000_1723122060">
<title>【津波注意報 すべて解除】日向灘の地震で宮崎・高知・鹿児島で津波観測</title>
<description><![CDATA[8月8日(木)16時43分に日向灘で発生したM7.1の地震により津波注意報が発表されていましたが、22時00分にすべて解除されました。<br><br>この地震により、宮崎県、高知県、鹿児島県で津波が観測されました。<br><a href="https://weathernews.jp/s/topics/202408/080255/" class="dmenu-non smartnews">» 南海トラフ地震臨時情報発表（気象庁） キーワード【調査中】</a><br><a href="https://weathernews.jp/tsunami/?fm=news" class="dmenu-non web smartnews">» 発表中の津波情報</a><a href="weathernews://weathernews.jp/tsunami" class="app">» 発表中の津波情報</a><br><a href="https://weathernews.jp/quake/?fm=news" class="dmenu-non web smartnews">» 地震情報一覧</a><a href="weathernews://weathernews.jp/quake" class="app">» 地震情報一覧</a><!-- 動画ここから<br> --><div class="dmenu-non smartnews"><br><h2>専門家 山口剛央による地震・津波の解説</h2><div style="background-color: #fff; border-radius: 8px; border: 1px solid #eee; overflow: hidden;"><a href="https://youtu.be/URmHzY4T4ww" style="text-decoration: none; color: black;" target="_blank"><div style="position: relative; line-height: 0px;"><img style="width: 100%;" alt="ウェザーニュースLiVE 解説アーカイブ" src="https://i.ytimg.com/vi/URmHzY4T4ww/maxresdefault.jpg"><div style="position: absolute; left: 50%; top: 50%; width: 68px; height: 48px; margin-left: -34px; margin-top: -24px;"><svg height="100%" version="1.1" viewBox="0 0 68 48" width="100%"><path d="M66.52,7.74c-0.78-2.93-2.49-5.41-5.42-6.19C55.79,.13,34,0,34,0S12.21,.13,6.9,1.55 C3.97,2.33,2.27,4.81,1.48,7.74C0.06,13.05,0,24,0,24s0.06,10.95,1.48,16.26c0.78,2.93,2.49,5.41,5.42,6.19 C12.21,47.87,34,48,34,48s21.79-0.13,27.1-1.55c2.93-0.78,4.64-3.26,5.42-6.19C67.94,34.95,68,24,68,24S67.94,13.05,66.52,7.74z" fill="#f00"></path><path d="M 45,24 27,14 27,34" fill="#fff"></path></svg></div></div><div style="padding: 8px;"><span style="color: gray;">youtube.com</span><br><span style="font-weight: bold;">ウェザーニュースLiVE 解説アーカイブ</span></div></a></div></div><!-- <br> 　動画ここまで --> ◆ 8月8日(木)16時43分に日向灘で発生したM7.1の地震により津波注意報が発表されていましたが、22時00分にすべて解除されました。この地震により、宮崎県、高知県、鹿児島県で津波が観測されました。]]></description>
<dc:date>2024-08-08T22:01:00+09:00</dc:date>
<link>https://weathernews.jp/s/topics/202408/080225/</link></item>
<item rdf:about="202408080255_1723112400_1723112700">
<title>南海トラフ地震臨時情報発表（気象庁） キーワード【巨大地震注意】</title>
<description><![CDATA[気象庁は今日8日(木)19時15分に、南海トラフ地震臨時情報を発表しました。キーワードは【巨大地震注意】です。<br><br>今後2週間程度、地震が発生したらすぐに避難できる準備をし、通常の生活を行ってください。<br><a href="https://weathernews.jp/s/topics/202408/080225/" class="dmenu-non smartnews">» 関連記事 津波情報</a><br><a href="https://weathernews.jp/quake/?fm=news" class="dmenu-non web smartnews">» 地震情報一覧</a><a href="weathernews://weathernews.jp/quake" class="app">» 地震情報一覧</a><br><a href="https://weathernews.jp/tsunami/?fm=news" class="dmenu-non web smartnews">» 発表中の津波情報</a><a href="weathernews://weathernews.jp/tsunami" class="app">» 発表中の津波情報</a><br><br>○「巨大地震注意」のキーワードの出る条件<br>　評価検討会により、監視領域内においてモーメントマグニチュード7.0以上の地震が発生したと評価された場合<br><br>→ 今回の地震は、モーメントマグニチュード7.0の地震と評価されました。今後は「南海トラフ地震関連解説情報」で地殻活動の状況等が発表されます。 ◆ 【南海トラフ地震臨時情報】気象庁は今日8日(木)19時15分に、南海トラフ地震臨時情報を発表しました。キーワードは【巨大地震注意】です。今後2週間程度、地震が発生したらすぐに避難できる準備をし、通常の生活を行ってください。]]></description>
<dc:date>2024-08-08T19:25:00+09:00</dc:date>
<link>https://weathernews.jp/s/topics/202408/080255/</link></item>
<item rdf:about="202408080265_1723111200_1723110600">
<title>震度6弱の宮崎県　明日も暑さ続く　天気急変にも注意</title>
<description><![CDATA[日向灘の地震で最大震度6弱を観測した宮崎県は明日9日(金)も厳しい暑さが続きます。大気の状態が不安定で、午後は雷雨にも注意が必要です。 ◆ 日向灘の地震で最大震度6弱を観測した宮崎県は明日9日(金)も厳しい暑さが続きます。大気の状態が不安定で、午後は雷雨にも注意が必要です。]]></description>
<dc:date>2024-08-08T18:50:00+09:00</dc:date>
<link>https://weathernews.jp/s/topics/202408/080265/</link></item>
<item rdf:about="202408080205_1723109400_1723109640">
<title>三連休は西日本から関東で猛暑　北日本は台風5号の動向注意</title>
<description><![CDATA[明後日10日(土)からの三連休は西日本や東海、関東で暑さが続き、熱中症対策が必須です。北日本は台風5号が接近する可能性があります。 ◆ 明後日10日(土)からの三連休は西日本や東海、関東で暑さが続き、熱中症対策が必須です。北日本は台風5号が接近する可能性があります。]]></description>
<dc:date>2024-08-08T18:34:00+09:00</dc:date>
<link>https://weathernews.jp/s/topics/202408/080205/</link></item>
<item rdf:about="202408080245_1723107000_1723106400">
<title>日向灘の地震で震度6弱を観測　M7.1は1984年以来の規模</title>
<description><![CDATA[8月8日(木)、日向灘を震源とするマグニチュード7.1の地震が発生し、最大震度6弱を観測しました。マグニチュード7クラスは1984年以来の規模です。 ◆ 8月8日(木)、日向灘を震源とするマグニチュード7.1の地震が発生し、最大震度6弱を観測しました。マグニチュード7クラスは1984年以来の規模です。]]></description>
<dc:date>2024-08-08T17:40:00+09:00</dc:date>
<link>https://weathernews.jp/s/topics/202408/080245/</link></item>
</rdf:RDF>
