<?xml version="1.0" encoding="utf-8"?><rdf:RDF xmlns="http://purl.org/rss/1.0/" xmlns:rdf="http://www.w3.org/1999/02/22-rdf-syntax-ns#" xmlns:dc="http://purl.org/dc/elements/1.1/" xmlns:content="http://purl.org/rss/1.0/modules/content/" >
<channel><title>お天気ニュース</title><dc:rights>portions by © ウェザーニュース</dc:rights></channel>
<item rdf:about="202207140065_1657857600_1657854720">
<title>今日7月15日(金)夜、月と土星が接近</title>
<description><![CDATA[今日15日(金)夜から16日(土)明け方にかけて、月齢16.0の満月に近い月と土星が接近して見えます。<br><br>気になる今夜の天気はどうなるでしょうか。 ◆ 今日15日(金)夜から16日(土)明け方にかけて、南東の空で月齢16.0の満月に近い月と土星が接近して見えます。]]></description>
<dc:date>2022-07-15T12:12:00+09:00</dc:date>
<link>https://weathernews.jp/s/topics/202207/140065/</link></item>
<item rdf:about="202207150135_1657855800_1657855800">
<title>宮城県は激しい雨による土砂災害に警戒　今夜から明日早朝が雨のピーク</title>
<description><![CDATA[東北は前線の接近に伴い、雨が強まってきました。特に宮城県は先日の大雨ですでに地盤が緩んでいるおそれがあるため、土砂災害の発生に警戒してください。 ◆ 東北は前線の接近に伴い、雨が強まってきました。福島県や宮城県の一部には大雨警報が発表中です。特に宮城県は先日の大雨ですでに地盤が緩んでいるおそれがあるため、土砂災害の発生に警戒してください。]]></description>
<dc:date>2022-07-15T12:30:00+09:00</dc:date>
<link>https://weathernews.jp/s/topics/202207/150135/</link></item>
<item rdf:about="202207140165_1657852500_1657851600">
<title>記録的な大雨をもたらす“線状降水帯”とは？</title>
<description><![CDATA[大雨や集中豪雨により大規模な水害が発生した際、その要因として「線状降水帯」という言葉が用いられることがあります。<br><br>具体的にはどのようなものなのでしょうか？　その発生メカニズムを解説します。 ◆ 大雨や集中豪雨により大規模な水害が発生した時に「線状降水帯」という言葉が用いられることがあります。具体的にはどのようなものなのか、その発生原因を解説します。]]></description>
<dc:date>2022-07-15T11:20:00+09:00</dc:date>
<link>https://weathernews.jp/s/topics/202207/140165/</link></item>
<item rdf:about="202207150125_1657851780_1657852080">
<title>九州は線状降水帯が発生するおそれ　関東も土砂降りの雨に注意</title>
<description><![CDATA[今夜から明日16日(土)にかけて広い範囲で強雨や落雷に注意が必要です。気象庁は九州で「線状降水帯」が発生して、災害発生の危険性が急激に高まるおそれがあると発表しました。<br><br>そのほか、西日本から東北でも大気の状態が不安定で、関東などで土砂降りの雨になっています。 ◆ 気象庁は今夜から明日16日(土)にかけて、九州で「線状降水帯」が発生して、災害発生の危険性が急激に高まるおそれがあると発表しました。そのほか、西日本から東北でも大気の状態が不安定で、広い範囲で強雨や落雷に注意が必要です。]]></description>
<dc:date>2022-07-15T11:28:00+09:00</dc:date>
<link>https://weathernews.jp/s/topics/202207/150125/</link></item>
<item rdf:about="202207150115_1657846800_1657849140">
<title>兵庫県の日本海沿岸に高潮警報　西日本中心に大潮で潮位高く浸水注意</title>
<description><![CDATA[7月14日(木)の満月の前後は大潮の時期にあたり、満潮の時間帯を中心に潮位が高くなり、海岸や河口付近の低い土地で浸水や冠水のおそれがあります。<br><br>兵庫県の日本海沿岸には高潮警報が発表されました。昼過ぎから夕方にかけて高潮に警戒してください。高潮警報は警戒レベル4相当の情報です。<br><a href="https://weathernews.jp/s/download/weathernewstouch.html?fm=news" class="dmenu-non web smartnews" onclick='javascript:ga_and_go(this.href,"文中リンク_アプリDL"); return false'>&raquo; 天気や季節のニュースをアプリで読む</a> ◆ 7月14日(木)の満月の前後は大潮の時期にあたり、満潮の時間帯を中心に潮位が高くなり、海岸や河口付近の低い土地で浸水や冠水のおそれがあります。兵庫県の日本海沿岸には高潮警報が発表されました。昼過ぎから夕方にかけて高潮に警戒してください。高潮警報は警戒レベル4相当の情報です。]]></description>
<dc:date>2022-07-15T10:39:00+09:00</dc:date>
<link>https://weathernews.jp/s/topics/202207/150115/</link></item>
<item rdf:about="202207150095_1657845780_1657845300">
<title>九州で非常に激しい雨　道路冠水や土砂災害に厳重警戒</title>
<description><![CDATA[今日15日(金)の九州は朝から局地的に雨が強まっています。活発な雨雲は午後にかけて北上する見込みで、各地で冠水や土砂災害に厳重な警戒が必要です。 ◆ 今日の九州は大気の状態が不安定になり、雨雲が発達して梅雨末期のような大雨になっています。鹿児島県や宮崎県には土砂災害警戒情報が発表中です。活発な雨雲は午後にかけて北上するため、各地で冠水や土砂災害に厳重に警戒してください。]]></description>
<dc:date>2022-07-15T09:35:00+09:00</dc:date>
<link>https://weathernews.jp/s/topics/202207/150095/</link></item>
<item rdf:about="202207150065_1657838700_1657839240">
<title>関東は今日も雨が降りやすい　局地的には土砂降りのおそれ</title>
<description><![CDATA[今日15日(金)も関東は雨の降りやすい状況が続きます。早朝は東京都心や千葉県周辺などでは雨の降っていないところがありますが、夜にかけて広範囲で雨となり、局地的に雨雲が発達して土砂降りになるところもある予想です。大きい傘を持ってお出かけください。 ◆ 今日15日(金)も関東は雨の降りやすい状況が続きます。早朝は東京都心や千葉県周辺などでは雨の降っていないところがありますが、夜にかけて広範囲で雨となり、局地的に雨雲が発達して土砂降りになるところもある予想です。大きい傘を持ってお出かけください。]]></description>
<dc:date>2022-07-15T07:54:00+09:00</dc:date>
<link>https://weathernews.jp/s/topics/202207/150065/</link></item>
<item rdf:about="202207150005_1657836000_1657836420">
<title>熱中症警戒アラート　広島県や福岡県など7つの県に発表　今日15日(金)対象</title>
<description><![CDATA[環境省と気象庁は、今日15日(金)を対象とした熱中症警戒アラートを、広島県や福岡県などの7県に対して発表しました。沖縄県の大東島地方では今日を対象にした発表は今年初めてです。<br><br>対象エリアでは特に熱中症のリスクが高くなるため、こまめな塩分・水分補給はもちろん、室内でも無理せずにエアコンを使用するなど、熱中症予防を万全に行ってください。 ◆ 環境省と気象庁は、今日15日(金)を対象とした熱中症警戒アラートを、広島県や福岡県などの7県に対して発表しました。対象エリアでは特に熱中症のリスクが高くなるため、熱中症予防を万全に行ってください。]]></description>
<dc:date>2022-07-15T07:07:00+09:00</dc:date>
<link>https://weathernews.jp/s/topics/202207/150005/</link></item>
<item rdf:about="202207150015_1657833900_1657830300">
<title>今日7月15日(金)の天気　関東など西日本から東北で雨　九州は大雨に警戒</title>
<description><![CDATA[<div style="border: 1px solid #004466; border-radius:12px; padding:.2em; color: #001044;"><div align="center"><b>■ 天気のポイント ■</b></div>・西日本から東北の広範囲で雨<br>・九州は大雨に警戒を<br>・北海道は道北で日差しが届く</div><br><br>今日15日(金)は日本付近には前線が停滞し、暖かく湿った空気が流れ込んできます。日本海に進んでくる寒冷渦の影響で大気の状態が不安定になり、雨雲が発達して各地で雨が強まる見込みです。<br><br>特に九州は大雨による道路冠水や河川の氾濫、土砂災害の発生などに警戒をしてください。 ◆ 今日15日(金)は日本付近には前線が停滞し、暖かく湿った空気が流れ込んできます。日本海に進んでくる寒冷渦の影響で大気の状態が不安定になり、雨雲が発達して各地で雨が強まる見込みです。特に九州は大雨による道路冠水や河川の氾濫、土砂災害の発生などに警戒をしてください。]]></description>
<dc:date>2022-07-15T05:25:00+09:00</dc:date>
<link>https://weathernews.jp/s/topics/202207/150015/</link></item>
<item rdf:about="202207150055_1657832100_1657832700">
<title>宮崎県で1時間に120mm以上の猛烈な雨　記録的短時間大雨情報</title>
<description><![CDATA[宮崎県で局地的に雨が強まっています。<br><br>気象庁は、えびの市付近で5時30分までの1時間に120mm以上の猛烈な雨が降ったとみられるとして、記録的短時間大雨情報を発表しました。<br><br>宮崎県付近では午前中にかけて、低地の浸水や土砂災害等に警戒してください。<br><a class="dmenu-non smartnews" href="https://weathernews.jp/onebox/radar/?fm=news" onclick='javascript:ga_and_go(this.href,"文中リンク_oneboxレーダー"); return false' style="text-decoration:underline; color:#2a25c6;">&raquo; 雨雲レーダー</a> ◆ 宮崎県で局地的に雨が強まっています。気象庁は、えびの市付近で5時30分までの1時間に120mm以上の猛烈な雨が降ったとみられるとして、記録的短時間大雨情報を発表しました。低地の浸水や土砂災害等に警戒してください。]]></description>
<dc:date>2022-07-15T06:05:00+09:00</dc:date>
<link>https://weathernews.jp/s/topics/202207/150055/</link></item>
<item rdf:about="202207150025_1657831800_1657830600">
<title>週間天気　週末は大雨のおそれ　三連休以降もすっきりしない空</title>
<description><![CDATA[<div style="border: 1px solid #004466; border-radius:12px; padding: .2em; color: #001044;"><div align="center"><b>■この先1週間のポイント■</b></div>・週末にかけて広範囲で大雨のおそれ<br>・三連休以降も曇りや雨が続く<br>・梅雨のような蒸し暑さ　熱中症注意</div> ◆ この先1週間の天気のポイントは「週末にかけて広範囲で大雨のおそれ」「三連休以降も曇りや雨が続く」「梅雨のような蒸し暑さ　熱中症注意」です。ウェザーニュースの最新の天気予報を随時確認してください。]]></description>
<dc:date>2022-07-15T05:30:00+09:00</dc:date>
<link>https://weathernews.jp/s/topics/202207/150025/</link></item>
<item rdf:about="202207150035_1657831740_1657832820">
<title>ひと目でわかる傘マップ　7月15日(金)</title>
<description><![CDATA[今日7月15日(金)の外出の際に傘の持参が必要なエリアを解説します。<br><a href="https://weathernews.jp/s/topics/202207/150015/" class="dmenu-non smartnews" onclick='javascript:ga_and_go(this.href,"傘マップ記事リンク"); return false'>＞＞関連記事 今日の天気予報</a> ◆ 今日雨が降るエリア、傘が必要なエリアを詳しく解説します。ウェザーニュース天気予報。]]></description>
<dc:date>2022-07-15T06:07:00+09:00</dc:date>
<link>https://weathernews.jp/s/topics/202207/150035/</link></item>
<item rdf:about="202207140085_1657831560_1657834560">
<title>7月15日(金)の洗濯天気予報　関東など各地で雨　外干しNG</title>
<description><![CDATA[今日15日(金)の天気で、洗濯物を外干しできるかどうかをお伝えします。 ◆ 今日の天気で洗濯物を外干しできるかどうかをお伝えします。乾くまでに何時間かかるか、洗濯物の種類によっての違いなど、ピンポイントの予報はウェザーニュースの「お洗濯情報」からご覧頂けます。]]></description>
<dc:date>2022-07-15T06:36:00+09:00</dc:date>
<link>https://weathernews.jp/s/topics/202207/140085/</link></item>
<item rdf:about="202207150045_1657831500_1657831800">
<title>お天気キャスター解説　7月15日(金)の天気</title>
<description><![CDATA[<div class="youtube"><iframe width="560" height="315" src="https://www.youtube.com/embed/01ZCirzqyXE" title="YouTube video player" frameborder="0" allow="accelerometer; autoplay; clipboard-write; encrypted-media; gyroscope; picture-in-picture" allowfullscreen></iframe></div>きょう7月15日(金)の全国の天気をウェザーニュースキャスター駒木結衣がお伝えします。 ◆ ウェザーニュースのお天気キャスターから、きょうの天気をお届けします。]]></description>
<dc:date>2022-07-15T05:50:00+09:00</dc:date>
<link>https://weathernews.jp/s/topics/202207/150045/</link></item>
<item rdf:about="202206140315_1657828800_1657828440">
<title>雨粒の形は滴じゃない!?　どんな形か知っていますか？</title>
<description><![CDATA[梅雨が戻ったような空模様が続いています。今日はどの時間帯にどれくらい雨が降るのか、毎日天気予報の確認が欠かせない人も多いのではないでしょうか。<br><br>ところで皆さん、雨がどんな形で降ってくるのか考えたことはありますか？<br><br>雨はきれいな滴(しずく)の形で降ってくるのではありません。雨粒の形に秘められた法則を、ウェザーニュースの気象予報士、山口剛央(やまぐち・たけひさ)が解説します。 ◆ 雨がどんな形で降ってくるのか考えたことはありますか？きれいな滴の形で降ってくるのではありません。雨粒の形に秘められた法則を、ウェザーニュースの気象予報士、山口剛央が解説します。]]></description>
<dc:date>2022-07-15T04:54:00+09:00</dc:date>
<link>https://weathernews.jp/s/topics/202206/140315/</link></item>
<item rdf:about="202207140225_1657789200_1657789320">
<title>九州は局地的に猛烈な雨のおそれ　非常に湿った空気が流入</title>
<description><![CDATA[九州は明日15日(金)から明後日16日(土)にかけて、局地的に猛烈な雨の降るおそれがあります。前線が停滞し、そこに向かって非常に湿った空気が流れ込む影響です。 ◆ 九州は明日15日(金)から明後日16日(土)にかけて、局地的に猛烈な雨の降るおそれがあります。前線が停滞し、そこに向かって非常に湿った空気が流れ込む影響です。]]></description>
<dc:date>2022-07-14T18:02:00+09:00</dc:date>
<link>https://weathernews.jp/s/topics/202207/140225/</link></item>
<item rdf:about="202207140215_1657787400_1657787760">
<title>熱中症警戒アラート　大分県や沖縄県など計3県に発表　明日15日(金)対象</title>
<description><![CDATA[環境省と気象庁は、明日15日(金)を対象とした熱中症警戒アラートを、大分県や鹿児島県奄美地方、沖縄県の計3県に対して発表しました。大東島地方での発表は今年初めてです。<br><br>対象エリアでは特に熱中症のリスクが高くなるため、こまめな塩分・水分補給はもちろん、室内でも無理せずにエアコンを使用するなど、熱中症予防を万全に行ってください。 ◆ 環境省と気象庁は、明日15日(金)を対象とした熱中症警戒アラートを、大分県や鹿児島県奄美地方、沖縄県の計3県に対して発表しました。対象エリアでは特に熱中症のリスクが高くなるため、熱中症予防を万全に行ってください。]]></description>
<dc:date>2022-07-14T17:36:00+09:00</dc:date>
<link>https://weathernews.jp/s/topics/202207/140215/</link></item>
<item rdf:about="202207140185_1657786200_1657784940">
<title>明日7月15日(金)の天気　西日本から東北の広範囲で雨　九州は特に大雨警戒</title>
<description><![CDATA[<div style="border: 1px solid #004466; border-radius:12px; padding:.2em; color: #001044;"><div align="center"><b>■ 天気のポイント ■</b></div>・西日本から東北の広範囲で雨<br>・九州は大雨に警戒を<br>・北海道は道北で日差しが届く</div><br>明日15日(金)は日本付近には前線が停滞し、暖かく湿った空気が流れ込んできます。日本海に進んでくる寒冷渦の影響で大気の状態が不安定になり、雨雲が発達して各地で雨が強まる見込みです。特に九州は大雨に警戒をしてください。 ◆ 明日15日(金)は日本付近には前線が停滞し、暖かく湿った空気が流れ込んできます。日本海に進んでくる寒冷渦の影響で大気の状態が不安定になり、雨雲が発達し、各地で雨が強まる見込みです。特に九州は大雨に警戒をしてください。]]></description>
<dc:date>2022-07-14T16:49:00+09:00</dc:date>
<link>https://weathernews.jp/s/topics/202207/140185/</link></item>
<item rdf:about="202207140105_1657785300_1657785840">
<title>7月15日(金)　各地の気温変化と最適な服装</title>
<description><![CDATA[今日と明日の気温変化を比較して、気温に適した服装をご提案します。ウェザーニュースの服装予報もご活用ください。 ◆ 今日と明日の気温変化を比較して、気温に適した服装をご提案します。ウェザーニュースの服装予報もご活用ください。]]></description>
<dc:date>2022-07-14T17:04:00+09:00</dc:date>
<link>https://weathernews.jp/s/topics/202207/140105/</link></item>
<item rdf:about="202207140205_1657785000_1657784940">
<title>東京都内で本降りの雨　今夜から明日朝は関東で土砂降りの所も</title>
<description><![CDATA[今日14日(木)は午後になって関東の所々に活発な雨雲が現れています。夕方になって東京湾周辺で雨雲が発達し、東京都内の一部でも本降りの雨です。 ◆ 午後になって関東の所々に活発な雨雲が現れています。夕方になって東京湾周辺で雨雲が発達し、東京都内の一部でも本降りの雨です。]]></description>
<dc:date>2022-07-14T16:49:00+09:00</dc:date>
<link>https://weathernews.jp/s/topics/202207/140205/</link></item>
<item rdf:about="202207140245_1657784700_1657790400">
<title>あす7月15日(金)のウェザーニュース お天気キャスター解説</title>
<description><![CDATA[<div class="youtube"></iframe><iframe width="560" height="315" src="https://www.youtube.com/embed/mVfDNzHB_AU"title="YouTube video player" frameborder="0" allow="accelerometer; autoplay; clipboard-write; encrypted-media; gyroscope; picture-in-picture" allowfullscreen></iframe></div>あす7月15日(金)の全国の天気をウェザーニュースキャスター大島璃音がお伝えします。 ◆ ウェザーニュースキャスターが天気予報を解説します。]]></description>
<dc:date>2022-07-14T18:20:00+09:00</dc:date>
<link>https://weathernews.jp/s/topics/202207/140245/</link></item>
<item rdf:about="202207140145_1657782000_1657781640">
<title>来週にかけて梅雨末期の大雨パターン　明日は九州で警戒を</title>
<description><![CDATA[日本海を進む低気圧や前線に向かって暖かく湿った空気が流れ込み、雨雲が発達しやすくなっています。梅雨の終盤に見られる大雨パターンが来週にかけて続く見込みで、各地で警戒が必要です。 ◆ 日本海を進む低気圧や、その南に形成される前線の影響で、西日本では一部で雨の強まっている所があります。午後にかけては雨の範囲が広がり、局地的な非常に激しい雨に警戒が必要です。]]></description>
<dc:date>2022-07-14T15:54:00+09:00</dc:date>
<link>https://weathernews.jp/s/topics/202207/140145/</link></item>
<item rdf:about="202207140125_1657780200_1657777740">
<title>気象庁1か月予報　7月終盤から本格的な夏空　厳しい暑さに</title>
<description><![CDATA[今日14日(木)、気象庁は7月16日から8月15日までの1か月予報を発表しました。<br><br>夏の暑さをもたらす太平洋高気圧が7月の終盤から勢力を強め、日本付近まで張り出す日が増える見込みです。8月の前半にかけては本格的な夏空となって、厳しい暑さが予想されます。 ◆ 気象庁は1か月予報を発表しました。夏の暑さをもたらす太平洋高気圧が7月の終盤から勢力を強め、日本付近まで張り出す日が増える見込みです。8月の前半にかけては本格的な夏空となって、厳しい暑さが予想されます。]]></description>
<dc:date>2022-07-14T14:49:00+09:00</dc:date>
<link>https://weathernews.jp/s/topics/202207/140125/</link></item>
<item rdf:about="202207140155_1657778100_1657778100">
<title>週間天気　週末にかけて大雨のおそれ、三連休以降もすっきりしない空</title>
<description><![CDATA[<div style="border: 1px solid #004466; border-radius:12px; padding: .2em; color: #001044;"><div align="center"><b>■この先1週間のポイント■</b></div>・週末にかけて広範囲で大雨のおそれ<br>・三連休以降も曇りや雨が続く<br>・梅雨のような蒸し暑さ　熱中症注意</div> ◆ この先1週間の天気のポイントは「週末にかけて広範囲で大雨のおそれ」「三連休以降も曇りや雨が続く」「梅雨のような蒸し暑さ　熱中症注意」です。ウェザーニュースの最新の天気予報を随時確認してください。]]></description>
<dc:date>2022-07-14T14:55:00+09:00</dc:date>
<link>https://weathernews.jp/s/topics/202207/140155/</link></item>
<item rdf:about="202207140135_1657774200_1657774080">
<title>近畿や中国で局地的に激しい雨　道路冠水や落雷などに警戒</title>
<description><![CDATA[日本海を進む低気圧に向かって暖かく湿った空気が流れ込み、局地的に雨雲が発達しています。西日本の日本海側で雨が激しく、道路冠水や落雷などに警戒が必要です。 ◆ 日本海を進む低気圧に向かって暖かく湿った空気が流れ込み、局地的に雨雲が発達しています。西日本の日本海側で雨が激しく、道路冠水や落雷などに警戒が必要です。]]></description>
<dc:date>2022-07-14T13:48:00+09:00</dc:date>
<link>https://weathernews.jp/s/topics/202207/140135/</link></item>
<item rdf:about="202207140115_1657764900_1657764840">
<title>関東、昼間は弱い雨が降りやすい　夕方以降は次第に本降りに</title>
<description><![CDATA[今日14日(木)の関東は朝から雲に覆われ、所々で弱い雨が降っています。夕方以降は次第に雨雲がまとまり、夜遅い時間ほど本降りとなりますので、傘は必須です。 ◆ 今日の関東は朝から雲に覆われ、所々で弱い雨が降っています。夕方以降は次第に雨雲がまとまり、夜遅い時間ほど本降りとなりますので、傘は必須です。]]></description>
<dc:date>2022-07-14T11:14:00+09:00</dc:date>
<link>https://weathernews.jp/s/topics/202207/140115/</link></item>
<item rdf:about="202207140095_1657761300_1657762020">
<title>西日本から東海、北陸は激しい雨に警戒　明日は関東、九州で強雨に</title>
<description><![CDATA[日本海を進む低気圧や、その南に形成される前線の影響で、西日本では一部で雨の強まっている所があります。午後にかけては雨の範囲が広がり、局地的な非常に激しい雨に警戒が必要です。 ◆ 日本海を進む低気圧や、その南に形成される前線の影響で、西日本では一部で雨の強まっている所があります。午後にかけては雨の範囲が広がり、局地的な非常に激しい雨に警戒が必要です。]]></description>
<dc:date>2022-07-14T10:27:00+09:00</dc:date>
<link>https://weathernews.jp/s/topics/202207/140095/</link></item>
<item rdf:about="202207140075_1657757400_1657757040">
<title>九州は早朝から厳しい暑さ　雨が降ると気温は急降下</title>
<description><![CDATA[今日14日(木)の九州は朝の早い時間から30℃以上の暑さになっています。ただ、この後は雨が降る予想で、雨とともに気温は大きく下がる見込みです。 ◆ 今日14日(木)の九州は朝の早い時間から30℃以上の暑さになっています。ただ、この後は雨が降る予想で、雨とともに気温は大きく下がる見込みです。]]></description>
<dc:date>2022-07-14T09:04:00+09:00</dc:date>
<link>https://weathernews.jp/s/topics/202207/140075/</link></item>
<item rdf:about="202207130105_1657755000_1657742400">
<title>雲を食べてみたい！を実現!?　涼を感じる「青空ゼリーケーキ」の作り方</title>
<description><![CDATA[このところ曇りや雨の天気の日が多く、晴れ渡る空が恋しくなったりしますね。空の青さや雲の流れは見飽きることはありません。ほかにも写真に撮るなど、空の感じ方、楽しみ方は人それぞれ。では、「食べられる空」はいかがでしょうか。美しい空を自分の手で作って食すという楽しみ方があったのです。 ◆ 空の青さや雲の流れは見飽きることはありません。そんな青空と白い雲に見とれているだけではなく、「食べてみたい」と思ったことはありませんか？この夢を実現した「青空ゼリーケーキ」の作り方を教えていただきました。]]></description>
<dc:date>2022-07-14T05:00:00+09:00</dc:date>
<link>https://weathernews.jp/s/topics/202207/130105/</link></item>
<item rdf:about="202207140055_1657749600_1657748580">
<title>広島県内で40mm/h超の雨　今日は近畿や東海も非常に激しい雨に警戒を</title>
<description><![CDATA[今日14日(木)は日本海に「寒冷渦」と呼ばれる上空に寒気を伴った低気圧が進み、南西から暖かく湿った空気が次々に流れ込んで、低気圧の周辺では大気の状態が非常に不安定です。<br><br>朝の時点で広島など中国地方を中心に雨雲が発達しており、広島県の都志見では6時4分までの1時間に42.0mmの激しい雨が降っています。<br><br>このあと、寒冷渦の東進に伴い雨の範囲は拡大していきます。<br><a class="dmenu-non smartnews" href="https://weathernews.jp/s/radar/rd_weathernewstouch_hiresradar.html?fm=news" onclick='javascript:ga_and_go(this.href,"文中リンク_oneboxレーダー"); return false'>&raquo; 最新の雨雲レーダー</a> ◆ 今日14日(木)は「寒冷渦」と呼ばれる上空に寒気を伴った低気圧の影響で、西から雨域が広がり、近畿や東海で非常に激しい雨のおそれがあります。夜遅くは関東も雷雨に注意。また週末にかけて大雨のリスクがあります。]]></description>
<dc:date>2022-07-14T06:43:00+09:00</dc:date>
<link>https://weathernews.jp/s/topics/202207/140055/</link></item>
</rdf:RDF>
